numgear/__init__.py
numgear/functions.py
numgear/utils/h5.py
numgear/utils/npk.py
numgear-0.0.1b2.post1.dev0.dist-info/licenses/LICENSE
numgear-0.0.1b2.post1.dev0.dist-info/METADATA
numgear-0.0.1b2.post1.dev0.dist-info/WHEEL
numgear-0.0.1b2.post1.dev0.dist-info/top_level.txt
numgear-0.0.1b2.post1.dev0.dist-info/RECORD
